Metadata-Version: 2.1
Name: hurllm
Version: 1.0.9
Summary: Closed source LLM model.
Home-page: https://hurllm.web.app
Author: hurdotcom
License: Proprietary Software
Project-URL: Source code, https://github.com/hurllm/hurllm1.0.0
Project-URL: Download, https://github.com/hurllm/hurllm1.0.0/archive/refs/heads/main.zip
Keywords: LLM,Transformers,Artificial Intelligence,NLP,GPT
License-File: LICENSE.txt
